{
    "Name" : "Titania",
    "Parent" : "Uranus",
    "Type" : "Satellite",

    "Gravitational Parameter" : { "magnitude": 228.2, "units": "km^3 / s^2" },
    "Mass" :                    { "magnitude": 0.00342, "units": "10^24 * kg" },
    "Equitorial Radius" :       { "magnitude": 788.9, "units": "km" },
    "Polar Radius" :            { "magnitude": 788.9, "units": "km" },
    "Crash Radius" :            { "magnitude": 1568.9, "units": "km" },
    "Sphere Of Influence" :     { "magnitude": 7.55070955998e-04, "units": "AU" },
    "J2" :                      { "magnitude": 0.0, "units": "" },
    "J3" :                      { "magnitude": 0.0, "units": "" },
    "Axial Tilt" :              { "magnitude": 0.0, "units": "deg" },
    "Rotation Rate" :           { "magnitude": 41.351424275146869, "units": "deg/day" },
    "Sidereal Peroid" :         { "magnitude": 8.70586, "units": "days" },

    "State" : {
        "Epoch" : "1980-01-01 00:00:00",
        "Semimajor Axis" : {
            "value" : { "magnitude": 436.30e3, "units": "km" },
            "rate" :  { "magnitude": 0.0, "units": "km/JC" }
        },
        "Eccentricity" : {
            "value" : { "magnitude": 0.0011, "units": "" },
            "rate" :  { "magnitude": 0.0, "units": "1/JC" }
        },
        "Inclination" : {
            "value" : { "magnitude": 0.08, "units": "deg" },
            "rate" :  { "magnitude": 0.0, "units": "deg/JC" }
        },
        "Right Ascension" : {
            "value" : { "magnitude": 99.771, "units": "deg" },
            "rate" :  { "magnitude": 663360.1, "units": "deg/JC" }
        },
        "Argument Of Perigee" : {
            "value" : { "magnitude": 24.17, "units": "deg" },
            "rate" :  { "magnitude": 1465712.68, "units": "deg/JC" }
        },
        "True Latitude" : {
            "value" : { "magnitude": 48.785, "units": "deg" },
            "rate" :  { "magnitude": 5438764533.33, "units": "deg/JC" }
        }
    }
}